finterion_investing_algorithm_framework/__init__.py
finterion_investing_algorithm_framework/order_executor.py
finterion_investing_algorithm_framework/ping_hook.py
finterion_investing_algorithm_framework/portfolio_provider.py
finterion_investing_algorithm_framework/utils.py
finterion_investing_algorithm_framework-0.22.0.dist-info/LICENSE
finterion_investing_algorithm_framework-0.22.0.dist-info/METADATA
finterion_investing_algorithm_framework-0.22.0.dist-info/WHEEL
finterion_investing_algorithm_framework-0.22.0.dist-info/RECORD
