Metadata-Version: 2.1
Name: finterion-investing-algorithm-framework
Version: 0.22.0
Summary: This is the official finterion plugin for the investing algorithm framework open source project.
Author: Marc van Duyn
Author-email: marc@finterion.com
Requires-Python: >=3.10,<4.0
Classifier: Programming Language :: Python :: 3
Classifier: Programming Language :: Python :: 3.10
Classifier: Programming Language :: Python :: 3.11
Classifier: Programming Language :: Python :: 3.12
Requires-Dist: finterion (>=0.8.8,<0.9.0)
Requires-Dist: investing-algorithm-framework (>=6.5.2)
